graphcalc/__init__.py
graphcalc/solvers.py
graphcalc/utils.py
graphcalc/core/__init__.py
graphcalc/core/basics.py
graphcalc/core/neighborhoods.py
graphcalc/data/__init__.py
graphcalc/data/data_generation.py
graphcalc/generators/__init__.py
graphcalc/generators/simple_graphs.py
graphcalc/invariants/__init__.py
graphcalc/invariants/classics.py
graphcalc/invariants/degree.py
graphcalc/invariants/domination.py
graphcalc/invariants/spectral.py
graphcalc/invariants/zero_forcing.py
graphcalc/polytopes/__init__.py
graphcalc/polytopes/core.py
graphcalc/polytopes/generators.py
graphcalc/polytopes/invariants.py
graphcalc/viz/__init__.py
graphcalc/viz/edges.py
graphcalc/viz/vertces.py
graphcalc-1.2.15.dist-info/licenses/LICENSE
graphcalc-1.2.15.dist-info/METADATA
graphcalc-1.2.15.dist-info/WHEEL
graphcalc-1.2.15.dist-info/top_level.txt
graphcalc-1.2.15.dist-info/RECORD
