Metadata-Version: 2.4
Name: graphcalc
Version: 1.2.15
Summary: A Python package for graph computation functions
Author-email: Randy Davila <rrd6@rice.edu>
License: MIT
Project-URL: Documentation, https://graphcalc.readthedocs.io/en/latest/
Project-URL: Source Code, https://github.com/randyrdavila/graphcalc
Project-URL: PyPI, https://pypi.org/project/graphcalc/
Keywords: graph theory,networkx,graph computation
Classifier: Programming Language :: Python :: 3
Classifier: License :: OSI Approved :: MIT License
Classifier: Operating System :: OS Independent
Requires-Python: >=3.7
License-File: LICENSE
Requires-Dist: numpy
Requires-Dist: networkx
Requires-Dist: pillow
Requires-Dist: PuLP
Requires-Dist: matplotlib
Requires-Dist: python-dateutil
Requires-Dist: pandas
Provides-Extra: dev
Requires-Dist: contourpy==1.3.2; extra == "dev"
Requires-Dist: cycler==0.12.1; extra == "dev"
Requires-Dist: fonttools==4.59.0; extra == "dev"
Requires-Dist: iniconfig==2.1.0; extra == "dev"
Requires-Dist: kiwisolver==1.4.8; extra == "dev"
Requires-Dist: matplotlib==3.10.3; extra == "dev"
Requires-Dist: networkx==3.5; extra == "dev"
Requires-Dist: numpy==2.3.1; extra == "dev"
Requires-Dist: packaging==25.0; extra == "dev"
Requires-Dist: pandas==2.3.1; extra == "dev"
Requires-Dist: pillow==11.3.0; extra == "dev"
Requires-Dist: pluggy==1.6.0; extra == "dev"
Requires-Dist: PuLP==3.2.1; extra == "dev"
Requires-Dist: Pygments==2.19.2; extra == "dev"
Requires-Dist: pyparsing==3.2.3; extra == "dev"
Requires-Dist: pytest==8.4.1; extra == "dev"
Requires-Dist: python-dateutil==2.9.0.post0; extra == "dev"
Requires-Dist: pytz==2025.2; extra == "dev"
Requires-Dist: six==1.17.0; extra == "dev"
Requires-Dist: tzdata==2025.2; extra == "dev"
Dynamic: license-file
